tgbsms/__init__.py
tgbsms/enums.py
tgbsms/exceptions.py
tgbsms/tgbsms.py
tgbsms-1.3.5.dist-info/LICENSE
tgbsms-1.3.5.dist-info/METADATA
tgbsms-1.3.5.dist-info/WHEEL
tgbsms-1.3.5.dist-info/top_level.txt
tgbsms-1.3.5.dist-info/RECORD
