Metadata-Version: 2.1
Name: tgbsms
Version: 1.3.5
Summary: Telegram Bot Short Message Service: Small requests wrapper to send message to chat via Telegram Bot API
Author-email: hntirgeam <kmacroviperaz@gmail.com>
Project-URL: Homepage, https://github.com/hntirgeam/tgbsms
Project-URL: Issues, https://github.com/hntirgeam/tgbsms/issues
Classifier: Programming Language :: Python :: 3
Classifier: License :: OSI Approved :: MIT License
Classifier: Operating System :: OS Independent
Requires-Python: >=3.10
License-File: LICENSE
Requires-Dist: requests >=2.32.3
Requires-Dist: environs >=11.0.0
